lightning_utilities/__about__.py
lightning_utilities/__init__.py
lightning_utilities/py.typed
lightning_utilities/cli/__init__.py
lightning_utilities/cli/__main__.py
lightning_utilities/cli/dependencies.py
lightning_utilities/core/__init__.py
lightning_utilities/core/apply_func.py
lightning_utilities/core/enums.py
lightning_utilities/core/imports.py
lightning_utilities/core/inheritance.py
lightning_utilities/core/overrides.py
lightning_utilities/core/rank_zero.py
lightning_utilities/docs/__init__.py
lightning_utilities/docs/formatting.py
lightning_utilities/docs/retriever.py
lightning_utilities/install/__init__.py
lightning_utilities/install/requirements.py
lightning_utilities/test/__init__.py
lightning_utilities/test/warning.py
lightning_utilities-0.15.0.dist-info/licenses/LICENSE
lightning_utilities-0.15.0.dist-info/METADATA
lightning_utilities-0.15.0.dist-info/WHEEL
lightning_utilities-0.15.0.dist-info/top_level.txt
lightning_utilities-0.15.0.dist-info/RECORD
