Metadata-Version: 2.4
Name: lightning-utilities
Version: 0.15.0
Summary: Lightning toolbox for across the our ecosystem.
Home-page: https://github.com/Lightning-AI/utilities
Download-URL: https://github.com/Lightning-AI/utilities
Author: Lightning AI et al.
Author-email: developer@lightning.ai
License: Apache-2.0
Project-URL: Bug Tracker, https://github.com/Lightning-AI/utilities/issues
Project-URL: Documentation, https://dev-toolbox.rtfd.io/en/latest/
Project-URL: Source Code, https://github.com/Lightning-AI/utilities
Keywords: Utilities,DevOps,CI/CD
Classifier: Environment :: Console
Classifier: Natural Language :: English
Classifier: Development Status :: 3 - Alpha
Classifier: Intended Audience :: Developers
Classifier: Operating System :: OS Independent
Classifier: Programming Language :: Python :: 3
Classifier: Programming Language :: Python :: 3.8
Classifier: Programming Language :: Python :: 3.9
Classifier: Programming Language :: Python :: 3.10
Classifier: Programming Language :: Python :: 3.11
Classifier: Programming Language :: Python :: 3.12
Classifier: Programming Language :: Python :: 3.13
Requires-Python: >=3.9
License-File: LICENSE
Requires-Dist: importlib-metadata>=4.0.0; python_version < "3.8"
Requires-Dist: packaging>=17.1
Requires-Dist: setuptools
Requires-Dist: typing_extensions
Provides-Extra: docs
Requires-Dist: requests>=2.0.0; extra == "docs"
Provides-Extra: typing
Requires-Dist: mypy>=1.0.0; extra == "typing"
Requires-Dist: types-setuptools; extra == "typing"
Provides-Extra: cli
Requires-Dist: jsonargparse[signatures]>=4.38.0; extra == "cli"
Requires-Dist: tomlkit; extra == "cli"
Dynamic: author
Dynamic: author-email
Dynamic: classifier
Dynamic: description
Dynamic: description-content-type
Dynamic: download-url
Dynamic: home-page
Dynamic: keywords
Dynamic: license
Dynamic: license-file
Dynamic: project-url
Dynamic: provides-extra
Dynamic: requires-dist
Dynamic: requires-python
Dynamic: summary
